odoo8_addon_account_asset_analytic-8.0.1.0.0-py2.7-nspkg.pth
odoo_addons/account_asset_analytic/__openerp__.py
odoo_addons/account_asset_analytic/__init__.py
odoo_addons/account_asset_analytic/README.rst
odoo_addons/account_asset_analytic/models/account_asset_depreciation_line.py
odoo_addons/account_asset_analytic/models/__init__.py
odoo_addons/account_asset_analytic/models/account_invoice_line.py
odoo_addons/account_asset_analytic/models/account_asset_asset.py
odoo_addons/account_asset_analytic/i18n/es.po
odoo_addons/account_asset_analytic/views/account_asset_asset_view.xml
odoo_addons/account_asset_analytic/tests/__init__.py
odoo_addons/account_asset_analytic/tests/test_account_asset.py
odoo_addons/account_asset_analytic/static/description/icon.png
odoo8_addon_account_asset_analytic-8.0.1.0.0.dist-info/top_level.txt
odoo8_addon_account_asset_analytic-8.0.1.0.0.dist-info/WHEEL
odoo8_addon_account_asset_analytic-8.0.1.0.0.dist-info/RECORD
odoo8_addon_account_asset_analytic-8.0.1.0.0.dist-info/metadata.json
odoo8_addon_account_asset_analytic-8.0.1.0.0.dist-info/DESCRIPTION.rst
odoo8_addon_account_asset_analytic-8.0.1.0.0.dist-info/METADATA
odoo8_addon_account_asset_analytic-8.0.1.0.0.dist-info/namespace_packages.txt
